{
  "fetched_at": "2026-07-15T10:53:38.508398+00:00",
  "period": {
    "since": "2026-04-01",
    "until": "2026-07-15"
  },
  "adset": {
    "27 - 55 | Engajamento 365D": {
      "2026-04": {
        "w1": 353.98,
        "w2": 322.42999999999995,
        "w3": 23.68
      }
    },
    "30 - 55 | SP/MG | Resort All-inclusive": {
      "2026-04": {
        "w1": 42.9,
        "w2": 234.01000000000002,
        "w3": 215.45,
        "w4": 267.97
      },
      "2026-05": {
        "w1": 109.96000000000001
      }
    },
    "30 - 55 | RJ/DF/MT/MS/GO | Resort All-inclusive (Iphone 13+)": {
      "2026-04": {
        "w1": 404.44,
        "w2": 317.84999999999997,
        "w3": 320.72,
        "w4": 399.95
      },
      "2026-05": {
        "w1": 258.6,
        "w2": 228.64999999999998,
        "w3": 42.019999999999996
      }
    },
    "30 - 55 | LokaLike 2% Compradores | IG": {
      "2026-04": {
        "w1": 38.07
      },
      "2026-05": {
        "w1": 107.87,
        "w2": 192.11,
        "w3": 140.81,
        "w4": 164.45
      },
      "2026-06": {
        "w1": 142.32,
        "w2": 137.16000000000003,
        "w3": 141.41,
        "w4": 360.44
      },
      "2026-07": {
        "w1": 280.37999999999994,
        "w2": 338.52000000000004,
        "w3": 7.63
      }
    },
    "26 - 50 | RO/AM/MS/MT/AP/TO/RR | Viajantes": {
      "2026-04": {
        "w3": 100.26
      }
    },
    "26 - 50 | LookaLike 2% Clientes IMR (Iphone 13+)": {
      "2026-04": {
        "w3": 136.5,
        "w4": 197.6
      },
      "2026-05": {
        "w1": 265.36,
        "w2": 246.22,
        "w3": 242.24,
        "w4": 538.7099999999999
      },
      "2026-06": {
        "w1": 392.4100000000001,
        "w2": 547.76,
        "w3": 552.91,
        "w4": 772.6300000000001
      },
      "2026-07": {
        "w1": 792.13,
        "w2": 888.7700000000001,
        "w3": 26.160000000000004
      }
    },
    "30 - 55 | RJ/DF/MT/MS/GO | Resort All-inclusive": {
      "2026-04": {
        "w4": 130.92999999999998
      },
      "2026-05": {
        "w1": 174.02999999999997,
        "w2": 16.79,
        "w3": 12.49,
        "w4": 32.6
      },
      "2026-06": {
        "w1": 1.39,
        "w2": 0.32,
        "w3": 0.49000000000000005,
        "w4": 3.24
      }
    },
    "26 - 50 | LookaLike Score A": {
      "2026-05": {
        "w1": 156.65,
        "w2": 231.22999999999996,
        "w3": 204.81,
        "w4": 397.68000000000006
      },
      "2026-06": {
        "w1": 285.56,
        "w2": 507.04,
        "w3": 568.1000000000001,
        "w4": 710.82
      },
      "2026-07": {
        "w1": 764.94,
        "w2": 876.4000000000001,
        "w3": 40.82
      }
    },
    "30 - 50 | BR | Profissões [+] viajantes frequentes": {
      "2026-05": {
        "w3": 160.01000000000002,
        "w4": 544.4599999999999
      },
      "2026-06": {
        "w1": 356.15999999999997,
        "w2": 306.02,
        "w3": 318.57000000000005,
        "w4": 551.74
      },
      "2026-07": {
        "w1": 494.78,
        "w2": 760.9100000000001,
        "w3": 16.560000000000002
      }
    },
    "30 - 50 | Videoview 50-95% | Topo de Funil [teste]": {
      "2026-05": {
        "w3": 171.19,
        "w4": 421.3
      },
      "2026-06": {
        "w1": 228.03,
        "w2": 218.34999999999997,
        "w3": 241.34,
        "w4": 300.46
      }
    },
    "26 - 50 | LookaLike 1% Clientes IMR (Iphone 13+)": {
      "2026-06": {
        "w3": 160.8,
        "w4": 549.6899999999999
      },
      "2026-07": {
        "w1": 790.21,
        "w2": 871.62,
        "w3": 28.87
      }
    },
    "26 - 50 | LookaLike 1% Clientes IMR (Iphone 13+) [LPA]": {
      "2026-06": {
        "w4": 2.48
      }
    }
  },
  "creative": {
    "VD02": {
      "2026-04": {
        "w1": 436.03999999999996,
        "w2": 459.56,
        "w3": 184.20999999999998,
        "w4": 109.73
      },
      "2026-05": {
        "w1": 261.17,
        "w2": 39.63,
        "w3": 340.57,
        "w4": 114.19999999999997
      },
      "2026-06": {
        "w1": 38.599999999999994,
        "w2": 9.98,
        "w3": 12.950000000000003,
        "w4": 84.44000000000001
      },
      "2026-07": {
        "w1": 808.08,
        "w2": 289.91999999999996,
        "w3": 16.34
      }
    },
    "VD01": {
      "2026-04": {
        "w1": 13.45,
        "w2": 3.6599999999999993,
        "w3": 4.92,
        "w4": 44.3
      },
      "2026-05": {
        "w1": 135.68,
        "w2": 20.689999999999998,
        "w3": 4.27,
        "w4": 100.46999999999998
      },
      "2026-06": {
        "w1": 6.54
      }
    },
    "BN02": {
      "2026-04": {
        "w1": 337.99,
        "w2": 401.22,
        "w3": 512.13,
        "w4": 659.79
      },
      "2026-05": {
        "w1": 40.779999999999994,
        "w2": 24.59,
        "w3": 4.8999999999999995,
        "w4": 327.44
      },
      "2026-06": {
        "w1": 269.48999999999995,
        "w2": 505.88000000000005,
        "w3": 562.62,
        "w4": 674.7300000000001
      },
      "2026-07": {
        "w1": 614.7600000000002,
        "w2": 1082.6900000000003,
        "w3": 17.93
      }
    },
    "BN01": {
      "2026-04": {
        "w1": 51.91,
        "w2": 9.850000000000001,
        "w3": 55.31,
        "w4": 35.989999999999995
      },
      "2026-05": {
        "w1": 255.43,
        "w2": 460.75999999999993,
        "w3": 86.96000000000001
      },
      "2026-06": {
        "w4": 32.94
      },
      "2026-07": {
        "w1": 157.35,
        "w2": 339.24,
        "w3": 14.86
      }
    },
    "VD03": {
      "2026-04": {
        "w3": 40.040000000000006,
        "w4": 78.51
      },
      "2026-05": {
        "w1": 77.60000000000001,
        "w2": 149.38,
        "w3": 20.61,
        "w4": 64.12
      },
      "2026-06": {
        "w1": 137.92,
        "w2": 143.60999999999999,
        "w3": 161.27999999999997,
        "w4": 275.23999999999995
      },
      "2026-07": {
        "w1": 44.94,
        "w2": 305.08,
        "w3": 30.11
      }
    },
    "BN03": {
      "2026-04": {
        "w4": 4.62
      },
      "2026-05": {
        "w1": 197.18,
        "w2": 219.69,
        "w3": 515.93,
        "w4": 1323.1999999999998
      },
      "2026-06": {
        "w1": 825.0,
        "w2": 949.9699999999998,
        "w3": 1121.3700000000001,
        "w4": 1894.8699999999997
      },
      "2026-07": {
        "w1": 969.6,
        "w2": 610.7000000000002,
        "w3": 16.17
      }
    },
    "VD04": {
      "2026-04": {
        "w4": 63.51
      },
      "2026-05": {
        "w1": 104.63,
        "w2": 0.26,
        "w3": 0.33,
        "w4": 7.709999999999999
      },
      "2026-06": {
        "w1": 1.12,
        "w2": 3.3200000000000003,
        "w3": 6.46,
        "w4": 6.31
      },
      "2026-07": {
        "w1": 0.2,
        "w2": 319.04,
        "w3": 1.54
      }
    },
    "VD04 - Motion (Depoimento)": {
      "2026-05": {
        "w4": 162.05999999999997
      },
      "2026-06": {
        "w1": 127.2,
        "w2": 103.88999999999999,
        "w3": 118.93999999999998,
        "w4": 124.60999999999996
      }
    },
    "19/06 - pov": {
      "2026-06": {
        "w4": 136.85
      },
      "2026-07": {
        "w1": 468.2999999999999,
        "w2": 635.47,
        "w3": 18.659999999999997
      }
    },
    "16/06 - objeções": {
      "2026-06": {
        "w4": 0.42000000000000004
      },
      "2026-07": {
        "w1": 10.08,
        "w2": 6.949999999999998
      }
    },
    "22/05 - direito de uso": {
      "2026-06": {
        "w4": 0.0
      },
      "2026-07": {
        "w1": 2.5,
        "w2": 1.3100000000000003
      }
    },
    "30/04 - comprei? e agora?": {
      "2026-06": {
        "w4": 10.18
      },
      "2026-07": {
        "w1": 19.67,
        "w2": 115.35000000000002,
        "w3": 3.0500000000000003
      }
    },
    "28/04 - custo de viagem": {
      "2026-06": {
        "w4": 1.95
      },
      "2026-07": {
        "w1": 4.14,
        "w2": 2.9099999999999997,
        "w3": 0.02
      }
    },
    "14/04 - especialista": {
      "2026-06": {
        "w4": 0.78
      },
      "2026-07": {
        "w1": 20.02,
        "w2": 17.85,
        "w3": 0.01
      }
    },
    "19/02 - Apresentação": {
      "2026-06": {
        "w4": 3.68
      },
      "2026-07": {
        "w1": 1.58,
        "w2": 3.61,
        "w3": 0.7
      }
    },
    "23/02 - Apresentação V2 (Leo)": {
      "2026-06": {
        "w4": 4.5
      },
      "2026-07": {
        "w1": 1.22,
        "w2": 6.02,
        "w3": 0.61
      }
    },
    "16/06 - objeções — Cópia": {
      "2026-07": {
        "w2": 0.08,
        "w3": 0.04
      }
    }
  },
  "adset_status": {
    "26 - 50 | LookaLike 1% Clientes IMR (Iphone 13+)": "ACTIVE",
    "26 - 50 | LookaLike 2% Clientes IMR (Iphone 13+)": "ACTIVE",
    "26 - 50 | LookaLike Score A": "ACTIVE",
    "30 - 50 | BR | Profissões [+] viajantes frequentes": "ACTIVE",
    "30 - 55 | LokaLike 2% Compradores | IG": "ACTIVE",
    "26 - 50 | LookaLike 1% Clientes IMR (Iphone 13+) [LPB]": "PAUSED",
    "30 - 50 | Videoview 50-95% | Topo de Funil [LPA]": "PAUSED",
    "26 - 50 | LookaLike Score A [LPA]": "PAUSED",
    "26 - 50 | LookaLike 1% Clientes IMR (Iphone 13+) [LPA]": "PAUSED",
    "30 - 50 | Videoview 50-95% | Topo de Funil [teste]": "PAUSED",
    "30 - 55 | RJ/DF/MT/MS/GO | Resort All-inclusive": "PAUSED",
    "26 - 50 | RO/AM/MS/MT/AP/TO/RR | Viajantes": "PAUSED",
    "30 - 55 | RJ/DF/MT/MS/GO | Resort All-inclusive (Iphone 13+)": "PAUSED",
    "30 - 55 | SP/MG | Resort All-inclusive": "PAUSED",
    "30 - 55 | LokaLike 4% IG IBR": "PAUSED",
    "30 - 55 | LokaLike 2% Lista de Clientes": "PAUSED",
    "30 - 55 | Interesses Geolocalizados [RESORTS]": "PAUSED",
    "27 - 55 | Engajamento 365D": "PAUSED",
    "30 - 55 | LokaLike % Site Lead 180D | IG": "PAUSED",
    "27 - 55 | LokaLike 2% Compradores | IG | [+] Família": "PAUSED",
    "27 - 55 | SP/MG/MT/PR/RS/DF | IG | [+] Profissões": "CAMPAIGN_PAUSED",
    "30 - 55 | Engajamento 60D": "CAMPAIGN_PAUSED",
    "27 - 55 | Engajamento MME (365D) | IG": "PAUSED",
    "27 - 55 | BR | IG | [+] Férias": "CAMPAIGN_PAUSED"
  },
  "creative_status": {
    "19/06 - pov": "ACTIVE",
    "14/04 - especialista": "ACTIVE",
    "28/04 - custo de viagem": "ACTIVE",
    "22/05 - direito de uso": "ACTIVE",
    "23/02 - Apresentação V2 (Leo)": "ACTIVE",
    "30/04 - comprei? e agora?": "ACTIVE",
    "19/02 - Apresentação": "ACTIVE",
    "16/06 - objeções": "ACTIVE",
    "16/06 - objeções — Cópia": "ACTIVE",
    "BN02": "ACTIVE",
    "VD02": "ACTIVE",
    "BN03": "ACTIVE",
    "BN01": "ACTIVE",
    "VD03": "ACTIVE",
    "VD04": "ACTIVE",
    "VD01": "PAUSED",
    "VD04 - Motion (Depoimento)": "CAMPAIGN_PAUSED",
    "16/02 - Depoimento": "ADSET_PAUSED",
    "17/03 - Não é um hotel": "PAUSED",
    "24/12 - Confiança": "PAUSED"
  },
  "creative_preview": {
    "19/06 - pov": "https://fb.me/1V4odilLQu117rp",
    "14/04 - especialista": "https://fb.me/20sCzVJIs5urgAB",
    "28/04 - custo de viagem": "https://fb.me/23obLpXzurK6Waw",
    "22/05 - direito de uso": "https://fb.me/26xrjG2d187wuPl",
    "23/02 - Apresentação V2 (Leo)": "https://fb.me/3620rer195e89qX",
    "30/04 - comprei? e agora?": "https://fb.me/2aUTv45CEDJEevW",
    "19/02 - Apresentação": "https://fb.me/1V4wW3V1G1ZXrFy",
    "16/06 - objeções": "https://fb.me/yphuIRx5nMjGPto",
    "16/06 - objeções — Cópia": "https://fb.me/2HFBDe94Rs1P4c6",
    "BN02": "https://fb.me/2oAcbuYVaKaqTlc",
    "VD02": "https://fb.me/yx4CC8oKha5gIBX",
    "BN03": "https://fb.me/2lNJRItZrhYvUuX",
    "BN01": "https://fb.me/2bQ9C8SNX35ifxG",
    "VD03": "https://fb.me/1V0EQJME19GitFv",
    "VD04": "https://fb.me/1R3GMdyyU39AR2c",
    "VD01": "https://fb.me/232CFEzalmBQf1a",
    "VD04 - Motion (Depoimento)": "https://fb.me/2lOeEJyToDcE5Vf",
    "16/02 - Depoimento": "https://fb.me/26jyKyY9qwdPV2q",
    "17/03 - Não é um hotel": "https://fb.me/21lXTzK2Arat2Wv",
    "24/12 - Confiança": "https://fb.me/ykVf1LXLcivx6L8"
  },
  "creative_preview_iframe": {
    "19/06 - pov": "https://business.facebook.com/ads/api/preview_iframe.php?d=AQJnpKYFrENQ6cR2jgjQkkpPkoQ0cq0fXBW2DtT7Skkp93YilPohsr5F378t1PD_yF_KKYefy_AfErEFrnuirQJ4H-xVZrBmjEXnkoJkaYDbITX52rK-GxJBV_x79Z2zGRxN9kdoEPyz_ga728AKfGe7zSTKdtitpJ3R6GoWKHUHJXvlYA_KLhjIM7nNzv08skkbXdiELyabvtzOW_hCFNmUmueJVQP3gdzsnWxhk5j52tWzr2DiYpVueAp_JI92WUiKrQy2uKzp0eATpxva0CFr4wWgHsa7-B68WCNSvD8V-iPT8F-1AaisoQ2x9O6adIioEuAUtTq7KBpf5Xr2_gh5n1LofMNXeTKTjB-X2NameqoGNZIo5gG2z1mIsGzoliSu6-84ehnMpKZizfzzS4GoMLMRiEGCXqz9CVWl1hV-vx1mCld11dt9o-21h3CQR3s&t=AQL6k37_vUm8IUM-xZM",
    "14/04 - especialista": "https://business.facebook.com/ads/api/preview_iframe.php?d=AQKESIhBX6871Rh7Ry_UeSLVwLIFpqork_mAOCzmqMNbeptQfYCJwoJR-wb1Zskzt8ry4eb5Lcfmjteetz7xuU2LDoi-925XMRMBkMu0inIFHYncFDu8OkyXEn3Qpq65EFUo6J2HmuS0y9WFNU_PbrZWLlezrhopQW1rcmMWZtr3jC5mMtRyxBweyV0-VCKbrxeEtgxF37v038Um4wl5rHOlbR5wAxx1ICUbwQlryj79Y7aS5T-V9f3ORJrCs0GkEbuX8LSith6tEaW4hMJ-u08cVK9bz5Gbt0EQ3k283aJf6AGRC-tUyysfroPCNJ0g_NYsyBOx7GDvhF0vSumcN-Qc5uqc9MrDNKpc-AZjwMS5WAX1D1S57C6IPViGG8OcnX4a6j2fIijxD4IHCpg3gq2S_Ws3zcdgplVbO1PjW72XJUR5BlJAMO59nYpBebwfqrg&t=AQIg6rRji5VDkm7YorQ",
    "28/04 - custo de viagem": "https://business.facebook.com/ads/api/preview_iframe.php?d=AQKsGUgkkzPEH5Tj2f5RA5fHaJ9ayXld6j_vobIrb-KmUFS9q3gWzsO2LuGa4PU29XtC2C7TPjLRNcN5cFyEcvOI35TOCFrWUvpmpGjax_wQ6To3B0go8W0FG0Y2C-EwUMgvmQIjcmds7rDudWtvZHcjyItDC7ilB9-b0mpeUGPr8Z2qLMGi1n2ABIqaJEQ_k1ZSLuZnzuQyihrrSRjQpQ1rVQhq6Pafd0-bOD-Lb7yUD3vM3iIFueAgeKpTT_yWggh2ZzwyhApAhOM6OBbNYzyf3a-R829wF8mAXtOuwmRgQ7yuvaCFPtkpxIz2q2InhbAicXXmRxk8vk3lbYvuwnDnpTG8pXnq1WxPPjxa1ErVO_eGNglLHB-v6v4XQE1PruMHNbf75h61jy2v4cdLSlC6tT-gUnnat-wpZNJMr1KGLlWBQ9Tlfypl5kZuxqjcXxc&t=AQKGW8NYbuWuz14XMG8",
    "22/05 - direito de uso": "https://business.facebook.com/ads/api/preview_iframe.php?d=AQK3xYrV5_da5eizNlijkynqK5O5qWhz8e93VGfteWFIDD2IVAJC-i6oMOGVp0EuYme6tbIJSdEC2iH4jLJTVuxKd_cOu6WtBE07CGpVzP79lqR1EBSRMLf_fMRSn_aT9qY8k4-yl-OibKb3HAz-FD2NWb_K9l4UblYLgx8gbYKzmmwQ1II3Rz_1ZhAMPi87ivCwAp7AYvYIrF_WJi8zC-PAak_TCH9hy2D0v7UbXhl8ZYSa5jvTEOXtyQILKtylw9-qF79YnA2DVOARJgSKPZaN9A-O1lDLfU7uu7NBEHxYvcIuSf-mQc5oODsvQhwjnEZF0gMOOwcwa7Vtz7K__TzXURZEzfOu-8_BpGoShh8KUCHduTGbpqGtDjmXfXQUuAeT9NdwI0R71C9UGLgnMXqG8MXB9hg2wNoRUAIZ8EjVCBgps_PaovUmI7EXfErpv8E&t=AQKfDZb4Ghs8joytNwQ",
    "23/02 - Apresentação V2 (Leo)": "https://business.facebook.com/ads/api/preview_iframe.php?d=AQJADO_5s4iAIZBQRiM3UQC-Y0fzKWTCc9tKrr_PCVBCAiXFrS6dDV-odh7SunfYLDg6hhzTBg6UTCXYMvcCb4891mna83uDK5b26qeNbzDcPVcuhlufytedsxGyEro_d79A77lZqhMjxmqv0qPwXaoNCYMPiBDeDL6MYzT-C3v7u3vjCHwYARJa8rEpA23JAjm0xJnAt34j60Gcj59ZcscQoV7qYZK8S2ZZWWSRi9LdUZE_S8HBv74y7Zyq4x_nZhGe6fK9yPH7VpfXRH5HJXUy2qzbCoE-JKGu9rU4yg5NxB2C5CL0dh7HUv96Z2uOJRMLW6xY44uEmqC_NrRhynglI1j3Pb_nzZYC2qjcQ5kL8oYY1U5BSDg5u7lwEfhuBZFAWKT8qDvtzqvCJYZchFjvgoVuMtHi-EvGgtnvlgHvvKxF6MzscNWp6K_DJF5cAP4&t=AQJb15lLBp387xAjLUU",
    "30/04 - comprei? e agora?": "https://business.facebook.com/ads/api/preview_iframe.php?d=AQIqUHhdjWfYiyb4dNBr5gDACeQacLUYW0gjnfXpcF8frBctOV145oCf0eQekOSq9QR7wxfqHagMUDZ2ehynmHLdLQMpX97jDwMhQrmFcc8RTi-zaYuTyWHImDKNrO8lvcvZAYyyadJbXYUeK-Fok4cDWZyAu7R5fAF6qVSim-Mxq9yOaLdsuMZNpM_kYDtNJkqduWKbTtEWU7EWLeiEfJF6LqA6kGAOXu2o3_VIIevu3SVSSbqkd2pv8kgwV3HkfAtyNpQFnq2AMh-duNp8wJ3ZCNWKuGFlmn4xqMbjAe9LDKgfrOfgIGh0TVcZGiVxhAnzCZ8j-DsdvE3NUnu0IvPFzNucW-QVsMu7_sNyVJms5w1ZyfxtoAGl8qqV6BNI2U4WDyfDzkxiXzXfxUQjcRY6fsBYgO1l-g2GjlvK4YhjI7Kv_ANiGYFCf8gz5nfndv4&t=AQImlz4k8AWUE8tnTdg",
    "19/02 - Apresentação": "https://business.facebook.com/ads/api/preview_iframe.php?d=AQL3JRsz8O1ux8ean7d2y_NnnUPwa-6jFPyCddQ9p6PkkdgmMuMXoW8DREpiEnUSGooJHVkOKsmy3J5l3FTRUEt6G7osnqRW-CPMTT7boqtFda4PZxFIEaHSY6ihYc9Sh2j7H-zsXRLrC-S9Scc74yZBgVnRm9ApFqQlb3GrQAdZzi6nJE1j0uHiibhj8zV-tsgnMQUYPKc6I_LS-VN7EuC8uevXFQm6qE3SvrnGVZGKQn_proPKRrwtBGVHxZgNIZAvbpAldH09FyVaPO9Mr6IyaTkeQnPJBvKf94tiP0ESSljwkVNREWTfC18NwrRwHyZY3KC4Gpzceq-byRVbVbBRhPmMnHNZsR-Mpw-jH7m-dn5znpzlEwFTADzHxALHY1lO7OJtGyoRLK8PzBCMMd2dEBmhM5QgXO0DMLolLOZVW-oM9sUFCgZYV6W_XcAgbaA&t=AQKA2P99qIQ_5pQUYwU",
    "16/06 - objeções": "https://business.facebook.com/ads/api/preview_iframe.php?d=AQIE2NFwCwOXizVEdCX-oEqAXp_hmuN4KP9pW_eKIpBRQXX9vMb4Vb0GM4f7jwNwh0igQ_uTBOSjMEFttZN5dWado1ZYJAo7PILstZomZd-zJ42TkDehpvxJAtI9oyGXkUrMsmD7hjG6EuY3V_sO4gs4lnfu1DTqeT_hkilWgZ3LhZIZvwR-LR7HRD4peAIY63pkDmIv3DXY_u5CRfGCrooK3PqvcLeZJ3kqDhwuU4FetzlBNEJT81H-UbrVIcKBw0jmvrfAxN4csCnLy9ahNswJ9nGsbyAsGJI331qMH9P5JlQ-vWlPB1mvNPYTkxWyoVMv63dew6pV7OXTZJDOXNrqKPtm9V62eFLIwBgrRRcZeYQpkmEA6HsrCMSqbH3tdm02tPDDr552kvCOW2jbi-0vNovQrz0gC71TiJ6QFVHb2HDNQCbrFwEUT_bImowpjwM&t=AQIoLTxiJC078vSM3fk",
    "16/06 - objeções — Cópia": "https://business.facebook.com/ads/api/preview_iframe.php?d=AQIKVZQD6WXpb16fEEmJYViOR5lExVspPqMmNp0WbBjSrmUd35KrBkiYSPRsDSzpJGNE6hYUo0Ovr6TZYs1N8yD4_YArQKOZKmNpGSde08uCRARkNR_7rV5s8uS_GmP0N4AZTzD1UAimwvDFw-OnVZrqft4zaJ5PcObp1w-NW8bG_UxozaNFKrEEN4ekaJy0avNtidVFjVVfG8N7GsHgkW_7r_CD6izPw4aCJx2FBv-tF-BqPjFC9PBtAbOzTuJYOt5EkEpNrKS-Gni8jzWIaARTTmwEMv7dagkWoWoO_BcO0O1XcdJveL7iT2R9x-UQFqrNhOrzwR5-ucznT28HctGgCB8z5tjihUDyrjsSc-eAxnkh9lgpJQTZPKfgLkEKnwh2iLvGn2ZfhylQCHhu7RYXvmEdmNlw2b570R5sX78GMRyDSwdpHHDVvzsc30g1e_Y&t=AQKm--_G5X2Pz0xiohg",
    "BN02": "https://business.facebook.com/ads/api/preview_iframe.php?d=AQLIxfBmB0TVtiRTq9DQtOBqaB8OBDTXFBy_qETmd6SPfQYHRwVHqLDRaf1BKrZRmBc7P99gSJ1NeUGDg0fbGM8nfjBHELgUIKVYPfsVz_8HpGORoRnDxMGfHmth-gJ9PPi8IJzGgTWeY7CZzbg7ghbqMbCLKITdFWoVBlIUA-eB-bdwDbbN4xT_RrVsjZbR6GZjIv0QRDpvmaDSBoocsBP7LFG7aJMmostut1_oSo7IzWu6AauN5jXo1cC8-2oXwo-c_-gnDExQeN_qJL4GzJg-xHlYS75dxCtYCeTqme1TlXMJ0StaOJzBFjpbKntEKy208nlCxUNzq1c2Pr3-mJ0scgMBBQ4qQbAqMfJdIRWGPVui5HsjDz6WpKZn4ixkSilY07g9U60NxjDGXZmT12D0TlSMpQPfZWiC3emP4aZyoBNnLTD6mO-bWbCSJovkS7g&t=AQJuRQMEYrb0bzTDuVg",
    "VD02": "https://business.facebook.com/ads/api/preview_iframe.php?d=AQI3XOTw99OhECvKVMhJWVrvEhPYBRzm801JukhvG_eJit8aIIwd48F0IjsBouyG8uMTwAiftRwhhdijKuNKfaJC2Nj74WcNKJFSk8N0_dNzZtvOiPUsLP2iGS92ZkzSfQAhz9phqOAlK4PlwCIEE-OhDj5kchWK8pPHTJAlxNPG7X-BjNN685zbhrZvaQABsPemwSpWf-cY6cG2UW2ELXeotnV694njubnViUeo504RhOqBe35QWuoysh7vQWRzx-83GLqHjt95pLiOzIKwOb6fKBHOTy-TGc0NAfRyiTb00Lds8efqqC8rihyOAShUzz2g6o27WN6N6rb9VtgXbcsi5ZL65_g57ESFxl52vtQ3Y5UQCoOu1NuFvpk8Ud94Zt_hV2A_gbDY7VmTXQt-eVzeT1Zc-jZXejLCPnW_lVSlX4mef5ACM6NKh_PPfSkSzno&t=AQKaXoutxK8fn5gLawU",
    "BN03": "https://business.facebook.com/ads/api/preview_iframe.php?d=AQKe12R1Eby9mbqd6-cqpR-m-l1t8QjY-zFivfXCcXt2xXgkmTfeqMIFYLCko_1hHrZOl1bksDIi0yLKB-JtLDG-K6yfiRn1X7MturE-qZ902ckr8qi2hrw8SRu7G_MenxReao_3P_0KQExXP8CGPIdfsPoYgNzgda05XdQhZQl5Djr6d4e308l6-1lrS79_VyjK3iZiMUFSeBXU4W3uPpBdj_oUuAWjiUnWAHcinncxTpP22F8esrr_dAyUz93SWZ9cmP22itLw7DX-s_ekNALuQp0XmFgGqDR2n2U04vamxGDSxoGaXGhxR6kQdvt_XdoxMf7FH7w1MLV1zNE-VInTurUuU9a1sTtljhg7sPQ1S6CjNvcDt4ofLrzmvefu6V_ei77Xy5QRGb3Am-afdC-9EHP2BnP9iH1A1Lzyn2_imFZEOIl2VXY7ZRWrI5kqFZw&t=AQLaHo82gM6JETlqvi0",
    "BN01": "https://business.facebook.com/ads/api/preview_iframe.php?d=AQJsmX7A5qIb8ld4jwMImRwBkklO3VQqJPy3kQfmeZ7C7qU4iTppQfXiO-euGRQ33aIjs_LMvfCCgkjseTCCzgI-kelwBtONj3gA8vimZRjOaXUhpygLypdRNkXGAcBFKaYJitcDpnJsBEx9OUcqcVkQo9bZPNIBRB_BIm7EYX9LIlmobS4a9MUOUd7aAKC7T49JZeeYCkYeochfw9RCI_PzP4NLX7_WIa3DWaktz0gwNEikFCoaGvwaiXEoO-FPv4AOs8Gg5-ifRuspRLvvQuH5Yw8fU48mD0fadn8-QX8empWImA-6E-rr3pxUCubtcYcKyAMya-bLAeBf9n5jv1XxISNIY58CIgdldnLm_Ie2Uo0AJJKGFybVvzSp9cM9hh0JPUwQ0V1Nd_KvVleSofnAvlBFNTgdD5liU988Ka3gukdAyCBAU-W05d36QxFfbRI&t=AQJuKuoCpQyJcoZI5zY",
    "VD03": "https://business.facebook.com/ads/api/preview_iframe.php?d=AQJMqP6HoL_grYu35R3MEDVLKlTVQkEeT07FaNANCgLD4PggB3O9rSfZVKY87bcqokjPkavYX3cI0mYYyE-RiAa3No9iN-XL6JElXfEUumgGZ0dPjKvbBTbnMKvU2XJZWjRf54I455z97B8Re33ft7Z0YpRZleN92c4Rvwm1tkiJ8s7lsfAPpjLc4kl9H9ihslC--LyuIWol7xUHpTv59-Rx-bG0Ifl_MQUcUWFTd_xzLLWmU-0TNXYQTPRmSNRUYxHuxlRgj-aCIYcztpA6ES0Tvyv35hufU6H0YcXAdhWTIF7fWxiIlpm9zUp0Ap6QwiIeVhjF2Fe-Suo8EHq01uRrjPgp4vdeG1DXcZGmRLzACO9ZZoZxxJ6hIIkEg9IonEFDsAi9YUUYhEiRKyLQSbBLOCmGd6WzEYyONW7aAZMxeD_sHMnesmVV-6SVrKkMuDg&t=AQKlFmIS9jqcbbmZj6I",
    "VD04": "https://business.facebook.com/ads/api/preview_iframe.php?d=AQLXfpfbVEbCfOuBtdzWLBfvO5jcv6m4OMZPpGO9rHblNtnnLYx-Ek536qt8plj9yDXHb8KjHadwj9O4kgdbXPKypSQeII_wSyZuCZlkIZRc5gzJ5vIRHha59JD9tAfSPU4FZSHrt2ZuRzc5pfkvj_RLiYFXS--88a2lTr5EwtkmXHcjTNC2J5ZI9U3a4K0dqMDwm0WudCTc4CH9c2Fe5YwSbav5Zc8DQczSyrJf-pdvkZQsKvp692S512XHMkB3f_KacMpbFT_Ui3dC0KB8lvVjhRuRAbinKZlll31OuWjcA_8R0-kwdo4-AlRbBpez2q5iqJU6PShxN1vXUVMplRvEglB0IPbesOpCO6s-Le3Kxlke43C5PFWF41XPnv8FEvIybz55dTipRY4LIU2C1GJo8SkTI3VikfjGN4oYFGhpwgd2_9CSBwEeJ-zUS64AlHY&t=AQK510W9TzV6aT0tVoY",
    "VD01": "https://business.facebook.com/ads/api/preview_iframe.php?d=AQLBfUbKF0iEs76YgTh8xM1SGOsZ7Qg9R4hF-506do6tUWQyz_OXI9K7L8IqbuiYFb1HFVflu41ULSs7k1kZAXpj7jGTnBJyG22Pi4yCMK-ERYmTRlrh-vSVF2zrehkUbTsVTSEmk-gNVzX8iJTcbq1S_2i-vshHmtsOoOD5W5y7ga3utqIoaD_t4bYkpACYGs-OGPKImA70jEbTm1NaK9oei2ZpJKtxzKBkaOg5r2MCvl3M2WBrQ9zcWqYx3CODvMVKoFykwJyi9BTLJdq2KlOAbyF17hpWRvSt1sYQzwfmvQt2OfpfAPdmCK7g47MNg76xd71wj1wzxXRv5cf8tOxMOivTR-pNovfGzdSD7HAHPpuyqT3WjxXj0uRLws8KIiavxhydTN7QyBGXnZ29TatjKcVL_MBWQ9u-qN0NKBCRaf726R9l5jUOxhAgON1BJ3s&t=AQKxeOtihj71t-cFar4",
    "VD04 - Motion (Depoimento)": "https://business.facebook.com/ads/api/preview_iframe.php?d=AQLJveASe7i9i5mJ6UA1vgE94hpxs2km6tZXBBoleoy2pg3NpJezoT7to6_Cm6VqWFIkl8JW0_usd3Zs8TMAdxEqGjWgR58SsQ2x1haCrO8pvVSsgZaCroVBcHfaRQgtoQfycwdVDJ5lFTL-dGdCG2ifHqRxa44wN4XRuoxnRFGK1hxysicge24du7E47DGWaifxjS2VNeTnU_ZQE5odWSk2z3S7aquK9LMRVGl1uZSJS4oU0fdy7OQdDXX-So6F2PQDutZpBsPDyYbbKcimk4PKamrLTkYCycwyioN_2BL3vJNWsGMSsxDfdCtmXhSePVuCabKyuU1g9dhasGOBDWrBDWwg6wKlwVDpgrpRyWEanPN9vehtQqn7SQcy9RKzRhRGiFeht0jvAElmsyEtX8zO6oJwdhVEw3gPIZcPCK4IptFB-kWVRRExM1a-StOnm8Q&t=AQIh_x2C2php1Paq7tw",
    "16/02 - Depoimento": "https://business.facebook.com/ads/api/preview_iframe.php?d=AQIDEUiAG-_yxr4u9jriPaTkU4y0CFFa5wDtO9QRQEtxHqBeL91oU1E38y0exhj5lyaOVcA0lyjGzra_offUqMceek-ZQsasDM9goBR7xCRc7Tv8kUPHeP7s721ibt9-f34v-Ssp3nQE7ICTUF9Yp6oAaDvr94iR3ZVG9KY2tSu1VkoCyinlu9g0gT6kaun4mdmJGDv7pMq4819Qdo-azj0OtS_vIlp4SvjEL20Y5NEnKGEbpfPf3BwKSB-409ZNEzmpNFIjt-R-8y8mcRQ7UBtwl6REj1Pa5SR4B73mrTKaOHcCy7AYTHagtJCJcjXI7ZTfr_lkbQ6UmbhVu7Wr2Ou3WIqbar1UFULqppVZGC4v3EFdJWzOvaOjEFPE1H2SX5YPSTyehaEq6ZQIYI2LgYRmwnKaahDD3e5JVZGrtMrVf3VDsMaGQzMMWUPzD3lLmLc&t=AQKOn_D4g7i1uFUrJMU",
    "17/03 - Não é um hotel": "https://business.facebook.com/ads/api/preview_iframe.php?d=AQKOLuNmOVPq6fp3OLVhNHTWBatCdZSXcImQf0C60c90zJfkvPz2ZYErz6h27_lB44ZwOj-5Vrr_ebaWdH76o4uq7f-3UrdYuoXJOEzhHR2UKBUXMXTHZ0EZ8gUb_sosxpGuq8WXiUSVUss2Jgd50SGXlHdISwQ65dDd5N2Ze4GsSwE-upv8l7U1XLDatvJ55hbQ0Ry8XjqYbyRlnU8XUtQA9gjhuxJ87lhYj1zXI75wkpTeeSB69ExA9p7i0PScC1xA_en8ifYFxthGs2etAXGJxdUbn3H0w3aWF4C4agL00RvcUJxL9syFlsdW9dlVW2GCxdcGPxDAyaxSkclujCnI9UrM2msqAQ4Xs7d03wJZEEPnO3nSVHluiiawv4MBmfYBc8aVp_GKmDcIC4OiX6wj62NQwuiF5R_81K8nUmCUeumO7fdCgMG6FS-Ba5SB0LY&t=AQI8ACHm7CwYuR4vNn4",
    "24/12 - Confiança": "https://business.facebook.com/ads/api/preview_iframe.php?d=AQI48G7NT5Se_FLZks_y3gQA4Upu5Yl3NnyQJJQY82UkZKi1iHBHMnLj7wKMqu6lpH7uW7qD66b7i_qnqpThEQwSN0Z4NtXViF78b0nU8eNDjvjQroaJ7dSaU5PfPTbPCA3BXBJgeZl5QM0tyZe3FUKtqumHBVuYTftexJ0RBWf6zBGOiv06ZeAQZuILl-Isg27QoQr9un2E5T7d4vgf89Xhih6wfiRpTfD1SC4XhtseMDddbDkQpm5GYWNY5piNVAjmKZGQcpvFJ8aEnI_vyEHLo3G9axBBuw22mcSRatD_5DkpKJBDqEIRkoBvVcacEcYlzm25U92wDWZysLdTW4FYvUGpqsun86eVC1wIwWAmD5YF7A3w-S9gR6IzhiHoZ0iWWj5R_mKw2fdXui21TlR-xKHb3FvF0L1LgGHlwsL7qrUx_zwqyKnu73UmeM0ysGg&t=AQLmrpOVZtapDBC44IQ"
  }
}